devdata/__init__.py
devdata/anonymisers.py
devdata/engine.py
devdata/extras.py
devdata/management/__init__.py
devdata/management/commands/__init__.py
devdata/management/commands/devdata_export.py
devdata/management/commands/devdata_import.py
devdata/pii_anonymisation.py
devdata/py.typed
devdata/reset_modes.py
devdata/settings.py
devdata/strategies.py
devdata/types.py
devdata/utils.py
django_devdata-1.1.0.dist-info/WHEEL
django_devdata-1.1.0.dist-info/METADATA
django_devdata-1.1.0.dist-info/LICENSE
django_devdata-1.1.0.dist-info/RECORD
