Metadata-Version: 2.1
Name: django-devdata
Version: 1.1.0
Summary: Django tooling for creating development databases seeded with anonymised production data.
Home-page: https://github.com/danpalmer/django-devdata
License: MIT
Keywords: django,development,databases
Author: Dan Palmer
Author-email: dan@danpalmer.me
Requires-Python: >=3.8
Classifier: License :: OSI Approved :: MIT License
Classifier: Programming Language :: Python :: 3
Classifier: Programming Language :: Python :: 3.8
Classifier: Programming Language :: Python :: 3.9
Classifier: Programming Language :: Python :: 3.10
Classifier: Programming Language :: Python :: 3.11
Requires-Dist: Faker (>=5.0.0)
Requires-Dist: tqdm (>=4.0.0)
Project-URL: Repository, https://github.com/danpalmer/django-devdata
